Metadata-Version: 1.0
Name: frodo
Version: 0.1
Summary: A high performance Python library for Hobbits
Home-page: https://github.com/second-breakfast/frodo
Author: Peregrin Took
Author-email: peregrin.took@example.com
License: MIT
Platform: UNKNOWN
